pluribus/__init__.py
pluribus/cli.py
pluribus/config.py
pluribus/display.py
pluribus/prompt.py
pluribus/status_file.py
pluribus/tasks.py
pluribus/worktree.py
pluribus_ai-0.1.1.dist-info/METADATA
pluribus_ai-0.1.1.dist-info/WHEEL
pluribus_ai-0.1.1.dist-info/entry_points.txt
pluribus_ai-0.1.1.dist-info/licenses/LICENSE
pluribus_ai-0.1.1.dist-info/RECORD
