Metadata-Version: 2.4
Name: pluribus-ai
Version: 0.1.1
Summary: Manage multiple parallel Claude Code instances working on different tasks
Author-email: Jai <jai@anthropic.com>
License: Apache-2.0
License-File: LICENSE
Requires-Python: >=3.9
Requires-Dist: click>=8.1.0
Requires-Dist: colorama>=0.4.6
Requires-Dist: pyyaml>=6.0
Requires-Dist: tabulate>=0.9.0
Requires-Dist: watchdog>=3.0.0
Provides-Extra: dev
Requires-Dist: black>=23.0; extra == 'dev'
Requires-Dist: mypy>=1.0; extra == 'dev'
Requires-Dist: pytest-cov>=4.0; extra == 'dev'
Requires-Dist: pytest>=7.0; extra == 'dev'
Requires-Dist: ruff>=0.1.0; extra == 'dev'
